amspy
