Metadata-Version: 1.0
Name: amspy
Version: 0.2.0
Summary: The amspy is a library to provide a simple Azure Media Services REST interface for python. This is a personal project and NOT an official implementation of the Azure Media Services SDK for python. The only purpose of this library is for educational purposes, so people can have an easy way to understand how to interact with cloud REST apis, and learn from the examples provided in this module as well as the debug information available in the logs. Any feedback, comments or bugs, please se
Home-page: http://github.com/msleal/amspy
Author: msleal
Author-email: msl@eall.com.br
License: MIT
Platform: UNKNOWN
